setup.py
cran/__init__.py
cran/settings.py
cran.egg-info/PKG-INFO
cran.egg-info/SOURCES.txt
cran.egg-info/dependency_links.txt
cran.egg-info/not-zip-safe
cran.egg-info/requires.txt
cran.egg-info/top_level.txt