Metadata-Version: 1.0
Name: cran
Version: 0.1
Summary: Cran via Native Python Library Wrapping
Home-page: http://github.com/mindey/cran
Author: Mindey I.
Author-email: mindey@qq.com
License: MIT
Platform: UNKNOWN
